{
  "kind": "club",
  "name": "PEC Zwolle",
  "imagePath": "Teams Images/Netherlands/Eredivisie/PEC Zwolle.png",
  "transfermarktClubId": 1269,
  "source": {
    "provider": "Transfermarkt",
    "apiBase": "https://tmapi-alpha.transfermarkt.technology",
    "season": {
      "seasonId": 2025,
      "label": "25/26",
      "cyclicalName": "2026"
    },
    "note": "Squad from tmapi; appearances/goals/assists from ceapi performance, summed across all competitions for the TM seasonId (current season).",
    "missingLogoFile": true
  },
  "goalkeepers": [
    {
      "name": "Jasper Schendelaar",
      "position": "Goalkeeper",
      "age": 25,
      "nationality": "Netherlands",
      "club": "PEC Zwolle",
      "appearances": 2,
      "goals": 0,
      "assists": 0
    },
    {
      "name": "Tom de Graaff",
      "position": "Goalkeeper",
      "age": 21,
      "nationality": "Netherlands",
      "club": "PEC Zwolle",
      "appearances": 27,
      "goals": 0,
      "assists": 0
    },
    {
      "name": "Duke Verduin",
      "position": "Goalkeeper",
      "age": 22,
      "nationality": "Netherlands",
      "club": "PEC Zwolle",
      "appearances": 2,
      "goals": 0,
      "assists": 0
    }
  ],
  "defenders": [
    {
      "name": "Anselmo García MacNulty",
      "position": "Centre-Back",
      "age": 23,
      "nationality": "Republic of Ireland",
      "club": "PEC Zwolle",
      "appearances": 28,
      "goals": 1,
      "assists": 0
    },
    {
      "name": "Simon Graves",
      "position": "Centre-Back",
      "age": 26,
      "nationality": "Denmark",
      "club": "PEC Zwolle",
      "appearances": 27,
      "goals": 0,
      "assists": 2
    },
    {
      "name": "Tijs Velthuis",
      "position": "Centre-Back",
      "age": 24,
      "nationality": "Netherlands",
      "club": "PEC Zwolle",
      "appearances": 8,
      "goals": 0,
      "assists": 0
    },
    {
      "name": "Damian van der Haar",
      "position": "Centre-Back",
      "age": 22,
      "nationality": "Netherlands",
      "club": "PEC Zwolle",
      "appearances": 2,
      "goals": 0,
      "assists": 0
    },
    {
      "name": "Sherel Floranus",
      "position": "Left-Back",
      "age": 27,
      "nationality": "Curaçao",
      "club": "PEC Zwolle",
      "appearances": 28,
      "goals": 1,
      "assists": 4
    },
    {
      "name": "Tristan Gooijer",
      "position": "Right-Back",
      "age": 21,
      "nationality": "Netherlands",
      "club": "PEC Zwolle",
      "appearances": 20,
      "goals": 3,
      "assists": 0
    },
    {
      "name": "Olivier Aertssen",
      "position": "Right-Back",
      "age": 21,
      "nationality": "Netherlands",
      "club": "PEC Zwolle",
      "appearances": 23,
      "goals": 0,
      "assists": 2
    },
    {
      "name": "David Voute",
      "position": "Right-Back",
      "age": 20,
      "nationality": "Netherlands",
      "club": "PEC Zwolle",
      "appearances": 4,
      "goals": 0,
      "assists": 0
    }
  ],
  "midfielders": [
    {
      "name": "Jadiel Pereira da Gama",
      "position": "Defensive Midfield",
      "age": 16,
      "nationality": "Netherlands",
      "club": "PEC Zwolle",
      "appearances": 14,
      "goals": 1,
      "assists": 0
    },
    {
      "name": "Ryan Thomas",
      "position": "Defensive Midfield",
      "age": 31,
      "nationality": "New Zealand",
      "club": "PEC Zwolle",
      "appearances": 24,
      "goals": 1,
      "assists": 0
    },
    {
      "name": "Nick Fichtinger",
      "position": "Defensive Midfield",
      "age": 21,
      "nationality": "Netherlands",
      "club": "PEC Zwolle",
      "appearances": 20,
      "goals": 1,
      "assists": 1
    },
    {
      "name": "Zico Buurmeester",
      "position": "Central Midfield",
      "age": 23,
      "nationality": "Netherlands",
      "club": "PEC Zwolle",
      "appearances": 22,
      "goals": 0,
      "assists": 0
    },
    {
      "name": "Jamiro Monteiro",
      "position": "Central Midfield",
      "age": 32,
      "nationality": "Cape Verde",
      "club": "PEC Zwolle",
      "appearances": 20,
      "goals": 2,
      "assists": 2
    },
    {
      "name": "Givaro Rahajaän",
      "position": "Central Midfield",
      "age": 18,
      "nationality": "Netherlands",
      "club": "PEC Zwolle",
      "appearances": 5,
      "goals": 0,
      "assists": 0
    },
    {
      "name": "Thijs Oosting",
      "position": "Attacking Midfield",
      "age": 25,
      "nationality": "Netherlands",
      "club": "PEC Zwolle",
      "appearances": 29,
      "goals": 6,
      "assists": 2
    },
    {
      "name": "Odysseus Velanas",
      "position": "Attacking Midfield",
      "age": 27,
      "nationality": "Netherlands",
      "club": "PEC Zwolle",
      "appearances": 6,
      "goals": 0,
      "assists": 0
    },
    {
      "name": "Gabriël Reiziger",
      "position": "Attacking Midfield",
      "age": 20,
      "nationality": "Netherlands",
      "club": "PEC Zwolle",
      "appearances": 17,
      "goals": 4,
      "assists": 0
    },
    {
      "name": "Samir Lagsir",
      "position": "Attacking Midfield",
      "age": 22,
      "nationality": "Netherlands",
      "club": "PEC Zwolle",
      "appearances": 3,
      "goals": 0,
      "assists": 1
    }
  ],
  "attackers": [
    {
      "name": "Shola Shoretire",
      "position": "Left Winger",
      "age": 22,
      "nationality": "England",
      "club": "PEC Zwolle",
      "appearances": 27,
      "goals": 6,
      "assists": 1
    },
    {
      "name": "Kaj de Rooij",
      "position": "Left Winger",
      "age": 25,
      "nationality": "Netherlands",
      "club": "PEC Zwolle",
      "appearances": 27,
      "goals": 7,
      "assists": 5
    },
    {
      "name": "Younes Namli",
      "position": "Right Winger",
      "age": 31,
      "nationality": "Denmark",
      "club": "PEC Zwolle",
      "appearances": 23,
      "goals": 2,
      "assists": 5
    },
    {
      "name": "Jan Faberski",
      "position": "Right Winger",
      "age": 19,
      "nationality": "Poland",
      "club": "PEC Zwolle",
      "appearances": 20,
      "goals": 0,
      "assists": 2
    },
    {
      "name": "Koen Kostons",
      "position": "Centre-Forward",
      "age": 26,
      "nationality": "Netherlands",
      "club": "PEC Zwolle",
      "appearances": 29,
      "goals": 12,
      "assists": 6
    },
    {
      "name": "Thomas Buitink",
      "position": "Centre-Forward",
      "age": 25,
      "nationality": "Netherlands",
      "club": "PEC Zwolle",
      "appearances": 7,
      "goals": 0,
      "assists": 0
    }
  ]
}
