{
  "kind": "club",
  "name": "FC Goa",
  "imagePath": "Teams Images/India/Indian Super League/FC Goa.png",
  "transfermarktClubId": 45321,
  "source": {
    "provider": "Transfermarkt",
    "apiBase": "https://tmapi-alpha.transfermarkt.technology",
    "season": {
      "seasonId": 2025,
      "label": "25/26",
      "cyclicalName": "2026"
    },
    "note": "Squad from tmapi; appearances/goals/assists from ceapi performance, summed across all competitions for the TM seasonId (current season).",
    "missingLogoFile": true
  },
  "goalkeepers": [
    {
      "name": "Hrithik Tiwari",
      "position": "Goalkeeper",
      "age": 24,
      "nationality": "India",
      "club": "FC Goa",
      "appearances": 15,
      "goals": 0,
      "assists": 0
    },
    {
      "name": "Lara Sharma",
      "position": "Goalkeeper",
      "age": 26,
      "nationality": "India",
      "club": "FC Goa",
      "appearances": 2,
      "goals": 0,
      "assists": 0
    },
    {
      "name": "Lionel Daryl Rymmei",
      "position": "Goalkeeper",
      "age": 20,
      "nationality": "India",
      "club": "FC Goa",
      "appearances": 0,
      "goals": 0,
      "assists": 0
    },
    {
      "name": "Bob Jackson",
      "position": "Goalkeeper",
      "age": 21,
      "nationality": "India",
      "club": "FC Goa",
      "appearances": 0,
      "goals": 0,
      "assists": 0
    }
  ],
  "defenders": [
    {
      "name": "Pol Moreno",
      "position": "Centre-Back",
      "age": 31,
      "nationality": "Spain",
      "club": "FC Goa",
      "appearances": 15,
      "goals": 1,
      "assists": 0
    },
    {
      "name": "Sandesh Jhingan",
      "position": "Centre-Back",
      "age": 32,
      "nationality": "India",
      "club": "FC Goa",
      "appearances": 12,
      "goals": 0,
      "assists": 0
    },
    {
      "name": "Ronney Willson Kharbudon",
      "position": "Centre-Back",
      "age": 23,
      "nationality": "India",
      "club": "FC Goa",
      "appearances": 6,
      "goals": 0,
      "assists": 0
    },
    {
      "name": "Nim Dorjee Tamang",
      "position": "Centre-Back",
      "age": 30,
      "nationality": "India",
      "club": "FC Goa",
      "appearances": 4,
      "goals": 0,
      "assists": 0
    },
    {
      "name": "Aakash Sangwan",
      "position": "Left-Back",
      "age": 30,
      "nationality": "India",
      "club": "FC Goa",
      "appearances": 16,
      "goals": 0,
      "assists": 1
    },
    {
      "name": "Jerry Lalrinzuala",
      "position": "Left-Back",
      "age": 27,
      "nationality": "India",
      "club": "FC Goa",
      "appearances": 3,
      "goals": 0,
      "assists": 0
    },
    {
      "name": "Seriton Fernandes",
      "position": "Right-Back",
      "age": 33,
      "nationality": "India",
      "club": "FC Goa",
      "appearances": 0,
      "goals": 0,
      "assists": 0
    },
    {
      "name": "Sitroy Carvalho",
      "position": "",
      "age": 20,
      "nationality": "India",
      "club": "FC Goa",
      "appearances": 2,
      "goals": 0,
      "assists": 0
    }
  ],
  "midfielders": [
    {
      "name": "Ayush Dev Chhetri",
      "position": "Defensive Midfield",
      "age": 22,
      "nationality": "India",
      "club": "FC Goa",
      "appearances": 14,
      "goals": 0,
      "assists": 1
    },
    {
      "name": "Sahil Tavora",
      "position": "Defensive Midfield",
      "age": 30,
      "nationality": "India",
      "club": "FC Goa",
      "appearances": 15,
      "goals": 1,
      "assists": 0
    },
    {
      "name": "Harsh Patre",
      "position": "Defensive Midfield",
      "age": 23,
      "nationality": "India",
      "club": "FC Goa",
      "appearances": 5,
      "goals": 0,
      "assists": 0
    },
    {
      "name": "Vellington Fernandes",
      "position": "Defensive Midfield",
      "age": 23,
      "nationality": "India",
      "club": "FC Goa II",
      "appearances": 0,
      "goals": 0,
      "assists": 0
    },
    {
      "name": "Raynier Fernandes",
      "position": "Central Midfield",
      "age": 30,
      "nationality": "India",
      "club": "FC Goa",
      "appearances": 4,
      "goals": 0,
      "assists": 0
    },
    {
      "name": "Boris Singh",
      "position": "Right Midfield",
      "age": 26,
      "nationality": "India",
      "club": "FC Goa",
      "appearances": 16,
      "goals": 0,
      "assists": 0
    },
    {
      "name": "Abdul Rabeeh A K",
      "position": "Right Midfield",
      "age": 25,
      "nationality": "India",
      "club": "FC Goa",
      "appearances": 16,
      "goals": 0,
      "assists": 1
    },
    {
      "name": "Brison Fernandes",
      "position": "Left Midfield",
      "age": 24,
      "nationality": "India",
      "club": "FC Goa",
      "appearances": 16,
      "goals": 2,
      "assists": 1
    },
    {
      "name": "Muhammad Nemil",
      "position": "",
      "age": 24,
      "nationality": "India",
      "club": "FC Goa",
      "appearances": 11,
      "goals": 0,
      "assists": 2
    },
    {
      "name": "Prachit Gaonkar",
      "position": "",
      "age": 19,
      "nationality": "India",
      "club": "FC Goa",
      "appearances": 4,
      "goals": 0,
      "assists": 0
    },
    {
      "name": "Malsawmtluanga",
      "position": "",
      "age": 21,
      "nationality": "India",
      "club": "FC Goa II",
      "appearances": 1,
      "goals": 0,
      "assists": 0
    }
  ],
  "attackers": [
    {
      "name": "Dejan Drazic",
      "position": "Left Winger",
      "age": 30,
      "nationality": "Serbia",
      "club": "FC Goa",
      "appearances": 16,
      "goals": 8,
      "assists": 3
    },
    {
      "name": "Udanta Singh",
      "position": "Right Winger",
      "age": 29,
      "nationality": "India",
      "club": "FC Goa",
      "appearances": 16,
      "goals": 0,
      "assists": 1
    },
    {
      "name": "Mohammed Yasir",
      "position": "Right Winger",
      "age": 27,
      "nationality": "India",
      "club": "FC Goa",
      "appearances": 3,
      "goals": 0,
      "assists": 0
    },
    {
      "name": "Daniel Lalhlimpuia",
      "position": "Centre-Forward",
      "age": 28,
      "nationality": "India",
      "club": "FC Goa",
      "appearances": 6,
      "goals": 0,
      "assists": 0
    },
    {
      "name": "Ishan Pandita",
      "position": "Centre-Forward",
      "age": 27,
      "nationality": "India",
      "club": "FC Goa",
      "appearances": 7,
      "goals": 1,
      "assists": 0
    },
    {
      "name": "Jovial Dias",
      "position": "",
      "age": 22,
      "nationality": "India",
      "club": "FC Goa II",
      "appearances": 0,
      "goals": 0,
      "assists": 0
    }
  ]
}
